odoo/addons/sale_commission_pricelist/README.rst
odoo/addons/sale_commission_pricelist/__init__.py
odoo/addons/sale_commission_pricelist/__manifest__.py
odoo/addons/sale_commission_pricelist/i18n/de.po
odoo/addons/sale_commission_pricelist/i18n/es.po
odoo/addons/sale_commission_pricelist/i18n/es_AR.po
odoo/addons/sale_commission_pricelist/i18n/fr.po
odoo/addons/sale_commission_pricelist/i18n/it.po
odoo/addons/sale_commission_pricelist/i18n/pt.po
odoo/addons/sale_commission_pricelist/i18n/pt_BR.po
odoo/addons/sale_commission_pricelist/i18n/sale_commission_pricelist.pot
odoo/addons/sale_commission_pricelist/i18n/tr.po
odoo/addons/sale_commission_pricelist/i18n/zh_CN.po
odoo/addons/sale_commission_pricelist/models/__init__.py
odoo/addons/sale_commission_pricelist/models/product_pricelist.py
odoo/addons/sale_commission_pricelist/models/sale_order_line.py
odoo/addons/sale_commission_pricelist/models/sale_order_line_agent.py
odoo/addons/sale_commission_pricelist/readme/CONTRIBUTORS.md
odoo/addons/sale_commission_pricelist/readme/DESCRIPTION.md
odoo/addons/sale_commission_pricelist/readme/USAGE.md
odoo/addons/sale_commission_pricelist/static/description/icon.png
odoo/addons/sale_commission_pricelist/static/description/icon.svg
odoo/addons/sale_commission_pricelist/static/description/index.html
odoo/addons/sale_commission_pricelist/tests/__init__.py
odoo/addons/sale_commission_pricelist/tests/test_sale_commission_pricelist.py
odoo/addons/sale_commission_pricelist/views/product_pricelist_view.xml
odoo_addon_sale_commission_pricelist-17.0.1.0.0.3.dist-info/METADATA
odoo_addon_sale_commission_pricelist-17.0.1.0.0.3.dist-info/WHEEL
odoo_addon_sale_commission_pricelist-17.0.1.0.0.3.dist-info/top_level.txt
odoo_addon_sale_commission_pricelist-17.0.1.0.0.3.dist-info/RECORD
